{
  "success": true,
  "data": {
    "id": "33333333-3333-4333-8333-333333333333",
    "applicationNo": "JTJC-202607-0001",
    "applicantUserId": "44444444-4444-4444-8444-444444444444",
    "applicantName": "张三",
    "applicantUnitId": "11111111-1111-4111-8111-111111111111",
    "applicantUnitName": "远望实业集团有限公司",
    "applicationDate": "2026-07-22",
    "applicationYear": 2026,
    "applicantDepartmentId": "55555555-5555-4555-8555-555555555555",
    "applicantDepartmentName": "投资管理部",
    "projectName": "集团新能源项目",
    "projectCode": "JT-XNY-2026-001",
    "projectLeaderUserId": "22222222-2222-4222-8222-222222222222",
    "projectLeaderName": "李四",
    "plannedStartDate": "2026-08-01",
    "plannedEndDate": "2027-07-31",
    "investmentEntityId": "11111111-1111-4111-8111-111111111111",
    "investmentEntityName": "远望实业集团有限公司",
    "investmentDirection": "STRATEGIC",
    "domesticOverseas": "DOMESTIC",
    "investmentMethod": "EQUITY",
    "majorProject": true,
    "currencyCode": "CNY",
    "projectTotalInvestment": "2000000.00",
    "plannedInvestment": "1200000.00",
    "expectedReturnRate": "8.5000",
    "fundingCompanyOwned": "800000.00",
    "fundingGroupRequested": "400000.00",
    "fundingSpecialBond": null,
    "fundingGovernment": null,
    "fundingLoan": null,
    "fundingOther": null,
    "annualPlannedInvestment": "1200000.00",
    "status": "IN_REVIEW",
    "currentStage": 1,
    "departmentHeadApproverId": "66666666-6666-4666-8666-666666666666",
    "supervisingLeaderApproverId": "77777777-7777-4777-8777-777777777777",
    "currentApproverUserId": "66666666-6666-4666-8666-666666666666",
    "version": 2,
    "history": [],
    "createdAt": "2026-07-22T07:00:00.000Z",
    "updatedAt": "2026-07-22T07:05:00.000Z"
  }
}
